README.rst
setup.py
openassets/__init__.py
openassets/protocol.py
openassets/transactions.py
openassets.egg-info/PKG-INFO
openassets.egg-info/SOURCES.txt
openassets.egg-info/dependency_links.txt
openassets.egg-info/requires.txt
openassets.egg-info/top_level.txt