Metadata-Version: 1.1
Name: openassets
Version: 1.0
Summary: Reference implementation of the Open Assets Protocol
Home-page: https://github.com/OpenAssets/openassets
Author: Flavien Charlon
Author-email: flavien@charlon.net
License: MIT License
Platform: UNKNOWN
Classifier: Development Status :: 5 - Production/Stable
Classifier: License :: OSI Approved :: MIT License
Classifier: Operating System :: OS Independent
Classifier: Programming Language :: Python :: 3
Classifier: Topic :: Software Development :: Libraries :: Python Modules
